GugeShenduXuexiBijiAhangchen/README.md
GugeShenduXuexiBijiAhangchen/__init__.py
GugeShenduXuexiBijiAhangchen/__main__.py
GugeShenduXuexiBijiAhangchen/file.epub
GugeShenduXuexiBijiAhangchen/index.html
GugeShenduXuexiBijiAhangchen/css/__init__.py
GugeShenduXuexiBijiAhangchen/css/annotations.css
GugeShenduXuexiBijiAhangchen/css/main.css
GugeShenduXuexiBijiAhangchen/css/normalize.css
GugeShenduXuexiBijiAhangchen/css/popup.css
GugeShenduXuexiBijiAhangchen/font/__init__.py
GugeShenduXuexiBijiAhangchen/font/fontello.eot
GugeShenduXuexiBijiAhangchen/font/fontello.svg
GugeShenduXuexiBijiAhangchen/font/fontello.ttf
GugeShenduXuexiBijiAhangchen/font/fontello.woff
GugeShenduXuexiBijiAhangchen/img/__init__.py
GugeShenduXuexiBijiAhangchen/img/annotator-glyph-sprite.png
GugeShenduXuexiBijiAhangchen/img/annotator-icon-sprite.png
GugeShenduXuexiBijiAhangchen/img/apple-touch-icon.png
GugeShenduXuexiBijiAhangchen/img/cancelfullscreen.png
GugeShenduXuexiBijiAhangchen/img/close.png
GugeShenduXuexiBijiAhangchen/img/fullscreen.png
GugeShenduXuexiBijiAhangchen/img/loader.gif
GugeShenduXuexiBijiAhangchen/img/menu-icon.png
GugeShenduXuexiBijiAhangchen/img/save.png
GugeShenduXuexiBijiAhangchen/img/saved.png
GugeShenduXuexiBijiAhangchen/img/settings-s.png
GugeShenduXuexiBijiAhangchen/img/settings.png
GugeShenduXuexiBijiAhangchen/img/star.png
GugeShenduXuexiBijiAhangchen/js/__init__.py
GugeShenduXuexiBijiAhangchen/js/epub.js
GugeShenduXuexiBijiAhangchen/js/epub.min.js
GugeShenduXuexiBijiAhangchen/js/epub.min.map
GugeShenduXuexiBijiAhangchen/js/hooks.min.js
GugeShenduXuexiBijiAhangchen/js/hooks.min.map
GugeShenduXuexiBijiAhangchen/js/reader.js
GugeShenduXuexiBijiAhangchen/js/reader.js.map
GugeShenduXuexiBijiAhangchen/js/reader.min.js
GugeShenduXuexiBijiAhangchen/js/reader.min.map
GugeShenduXuexiBijiAhangchen/js/hooks/__init__.py
GugeShenduXuexiBijiAhangchen/js/hooks/extensions/__init__.py
GugeShenduXuexiBijiAhangchen/js/hooks/extensions/highlight.js
guge_shendu_xuexi_biji_ahangchen-2024.3.4.0.dist-info/METADATA
guge_shendu_xuexi_biji_ahangchen-2024.3.4.0.dist-info/WHEEL
guge_shendu_xuexi_biji_ahangchen-2024.3.4.0.dist-info/entry_points.txt
guge_shendu_xuexi_biji_ahangchen-2024.3.4.0.dist-info/top_level.txt
guge_shendu_xuexi_biji_ahangchen-2024.3.4.0.dist-info/RECORD
